takenoko/__init__.py
takenoko/__main__.py
takenoko/data/takenoko.json
takenoko/data/takenoko/kinoko.json
takenoko-1.14.0.data/scripts/takenoko
takenoko-1.14.0.dist-info/LICENSE
takenoko-1.14.0.dist-info/METADATA
takenoko-1.14.0.dist-info/WHEEL
takenoko-1.14.0.dist-info/top_level.txt
takenoko-1.14.0.dist-info/RECORD
